[
  {
    "full_name": "Significant-Gravitas/AutoGPT",
    "stargazers_count": 177593,
    "open_issues_count": 208,
    "forks_count": 45918
  },
  {
    "full_name": "kiwibrowser/src.next",
    "stargazers_count": 3102,
    "open_issues_count": 651,
    "forks_count": 460
  },
  {
    "full_name": "beckn/protocol-specifications",
    "stargazers_count": 435,
    "open_issues_count": 49,
    "forks_count": 124
  },
  {
    "full_name": "EniasCailliau/GirlfriendGPT",
    "stargazers_count": 2656,
    "open_issues_count": 31,
    "forks_count": 451
  },
  {
    "full_name": "Zondax/filecoin-solidity",
    "stargazers_count": 97,
    "open_issues_count": 12,
    "forks_count": 44
  },
  {
    "full_name": "hcheng826/arc-contracts",
    "stargazers_count": 1,
    "open_issues_count": 5,
    "forks_count": 1
  },
  {
    "full_name": "JaisPiyush/arc-ip",
    "stargazers_count": 1,
    "open_issues_count": 1,
    "forks_count": 0
  },
  {
    "full_name": "ChainAgnostic/namespaces",
    "stargazers_count": 63,
    "open_issues_count": 24,
    "forks_count": 81
  },
  {
    "full_name": "lua/lua",
    "stargazers_count": 9296,
    "open_issues_count": 0,
    "forks_count": 1785
  }
]